itch_dl/__init__.py
itch_dl/__main__.py
itch_dl/api.py
itch_dl/cli.py
itch_dl/config.py
itch_dl/consts.py
itch_dl/downloader.py
itch_dl/handlers.py
itch_dl/infobox.py
itch_dl/keys.py
itch_dl/utils.py
itch_dl-0.6.1.dist-info/METADATA
itch_dl-0.6.1.dist-info/WHEEL
itch_dl-0.6.1.dist-info/entry_points.txt
itch_dl-0.6.1.dist-info/licenses/LICENSE
itch_dl-0.6.1.dist-info/RECORD
