Metadata-Version: 2.4
Name: itch-dl
Version: 0.6.1
Summary: itch.io bulk game downloader
Project-URL: GitHub, https://github.com/DragoonAethis/itch-dl
Project-URL: Wiki, https://github.com/DragoonAethis/itch-dl/wiki
Project-URL: Issues, https://github.com/DragoonAethis/itch-dl/issues
Project-URL: Donate, https://ko-fi.com/dragoonaethis
Author-email: Dragoon Aethis <dragoon@dragonic.eu>
License-Expression: MIT
License-File: LICENSE
Classifier: Development Status :: 4 - Beta
Classifier: Environment :: Console
Classifier: Topic :: Games/Entertainment
Classifier: Topic :: System :: Archiving :: Backup
Classifier: Topic :: Utilities
Classifier: Typing :: Typed
Requires-Python: ~=3.10
Requires-Dist: beautifulsoup4<5,>=4.13.3
Requires-Dist: lxml<6,>=5.3.1
Requires-Dist: requests<3,>=2.32.3
Requires-Dist: tqdm<5,>=4.67.1
Requires-Dist: urllib3<3,>=2.3.0
